jw_plyflatten/__about__.py
jw_plyflatten/__init__.py
jw_plyflatten/rasterization.py
jw_plyflatten/utils.py
lib/libplyflatten.so
jw_plyflatten-0.1.2.dist-info/LICENSE
jw_plyflatten-0.1.2.dist-info/METADATA
jw_plyflatten-0.1.2.dist-info/WHEEL
jw_plyflatten-0.1.2.dist-info/entry_points.txt
jw_plyflatten-0.1.2.dist-info/top_level.txt
jw_plyflatten-0.1.2.dist-info/RECORD
