Metadata-Version: 2.1
Name: jw-plyflatten
Version: 0.1.2
Summary: Take a series of ply files and produce a digital elevation map
Home-page: https://github.com/JaeWangL/plyflatten
Download-URL: https://pypi.org/project/jw-plyflatten
Author: JaeWang Lee
Author-email: JaeWangL <jnso5072@outlook.kr>
Project-URL: Bug Tracker, https://github.com/JaeWangL/plyflatten/issues
Project-URL: Source Code, https://github.com/JaeWangL/plyflatten
Requires-Python: >=3.6
License-File: LICENSE
Requires-Dist: affine
Requires-Dist: numpy
Requires-Dist: plyfile
Requires-Dist: pyproj
Requires-Dist: rasterio
Provides-Extra: dev
Requires-Dist: bump2version ; extra == 'dev'
Requires-Dist: pre-commit ; extra == 'dev'
Provides-Extra: test
Requires-Dist: pytest ; extra == 'test'
Requires-Dist: pytest-cov ; extra == 'test'
